README.md
setup.py
askky/client.py
askky.egg-info/PKG-INFO
askky.egg-info/SOURCES.txt
askky.egg-info/dependency_links.txt
askky.egg-info/requires.txt
askky.egg-info/top_level.txt